residueclasses/__init__.py
residueclasses-0.2.0.dist-info/LICENSE.md
residueclasses-0.2.0.dist-info/METADATA
residueclasses-0.2.0.dist-info/WHEEL
residueclasses-0.2.0.dist-info/top_level.txt
residueclasses-0.2.0.dist-info/RECORD
